{"v":3,"stories":{"configure-your-project--docs":{"id":"configure-your-project--docs","title":"Configure your project","name":"Docs","importPath":"./src/stories/Configure.mdx","storiesImports":[],"tags":["unattached-mdx","docs"],"kind":"Configure your project","story":"Docs","parameters":{"__id":"configure-your-project--docs","docsOnly":true,"fileName":"./src/stories/Configure.mdx"}},"my-examples-counter--docs":{"id":"my-examples-counter--docs","title":"My_Examples/Counter","name":"Docs","importPath":"./src/components/Counter/Counter.stories.tsx","tags":["autodocs","docs"],"storiesImports":[],"kind":"My_Examples/Counter","story":"Docs","parameters":{"__id":"my-examples-counter--docs","docsOnly":true,"fileName":"./src/components/Counter/Counter.stories.tsx"}},"my-examples-counter--counter-value-0":{"id":"my-examples-counter--counter-value-0","name":"Counter Value 0","title":"My_Examples/Counter","importPath":"./src/components/Counter/Counter.stories.tsx","tags":["autodocs","story"],"kind":"My_Examples/Counter","story":"Counter Value 0","parameters":{"__id":"my-examples-counter--counter-value-0","docsOnly":false,"fileName":"./src/components/Counter/Counter.stories.tsx"}},"my-examples-counter--counter-value-10":{"id":"my-examples-counter--counter-value-10","name":"Counter Value 10","title":"My_Examples/Counter","importPath":"./src/components/Counter/Counter.stories.tsx","tags":["autodocs","story"],"kind":"My_Examples/Counter","story":"Counter Value 10","parameters":{"__id":"my-examples-counter--counter-value-10","docsOnly":false,"fileName":"./src/components/Counter/Counter.stories.tsx"}},"my-examples-counter--counter-value-20":{"id":"my-examples-counter--counter-value-20","name":"Counter Value 20","title":"My_Examples/Counter","importPath":"./src/components/Counter/Counter.stories.tsx","tags":["autodocs","story"],"kind":"My_Examples/Counter","story":"Counter Value 20","parameters":{"__id":"my-examples-counter--counter-value-20","docsOnly":false,"fileName":"./src/components/Counter/Counter.stories.tsx"}},"example-button--docs":{"id":"example-button--docs","title":"Example/Button","name":"Docs","importPath":"./src/stories/Button.stories.ts","tags":["autodocs","docs"],"storiesImports":[],"kind":"Example/Button","story":"Docs","parameters":{"__id":"example-button--docs","docsOnly":true,"fileName":"./src/stories/Button.stories.ts"}},"example-button--primary":{"id":"example-button--primary","name":"Primary","title":"Example/Button","importPath":"./src/stories/Button.stories.ts","tags":["autodocs","story"],"kind":"Example/Button","story":"Primary","parameters":{"__id":"example-button--primary","docsOnly":false,"fileName":"./src/stories/Button.stories.ts"}},"example-button--secondary":{"id":"example-button--secondary","name":"Secondary","title":"Example/Button","importPath":"./src/stories/Button.stories.ts","tags":["autodocs","story"],"kind":"Example/Button","story":"Secondary","parameters":{"__id":"example-button--secondary","docsOnly":false,"fileName":"./src/stories/Button.stories.ts"}},"example-button--large":{"id":"example-button--large","name":"Large","title":"Example/Button","importPath":"./src/stories/Button.stories.ts","tags":["autodocs","story"],"kind":"Example/Button","story":"Large","parameters":{"__id":"example-button--large","docsOnly":false,"fileName":"./src/stories/Button.stories.ts"}},"example-button--small":{"id":"example-button--small","name":"Small","title":"Example/Button","importPath":"./src/stories/Button.stories.ts","tags":["autodocs","story"],"kind":"Example/Button","story":"Small","parameters":{"__id":"example-button--small","docsOnly":false,"fileName":"./src/stories/Button.stories.ts"}},"example-header--docs":{"id":"example-header--docs","title":"Example/Header","name":"Docs","importPath":"./src/stories/Header.stories.ts","tags":["autodocs","docs"],"storiesImports":[],"kind":"Example/Header","story":"Docs","parameters":{"__id":"example-header--docs","docsOnly":true,"fileName":"./src/stories/Header.stories.ts"}},"example-header--logged-in":{"id":"example-header--logged-in","name":"Logged In","title":"Example/Header","importPath":"./src/stories/Header.stories.ts","tags":["autodocs","story"],"kind":"Example/Header","story":"Logged In","parameters":{"__id":"example-header--logged-in","docsOnly":false,"fileName":"./src/stories/Header.stories.ts"}},"example-header--logged-out":{"id":"example-header--logged-out","name":"Logged Out","title":"Example/Header","importPath":"./src/stories/Header.stories.ts","tags":["autodocs","story"],"kind":"Example/Header","story":"Logged Out","parameters":{"__id":"example-header--logged-out","docsOnly":false,"fileName":"./src/stories/Header.stories.ts"}},"my-components-ui-mylabel--docs":{"id":"my-components-ui-mylabel--docs","title":"My_Components/UI/MyLabel","name":"Docs","importPath":"./src/stories/MyLabel.stories.ts","tags":["autodocs","docs"],"storiesImports":[],"kind":"My_Components/UI/MyLabel","story":"Docs","parameters":{"__id":"my-components-ui-mylabel--docs","docsOnly":true,"fileName":"./src/stories/MyLabel.stories.ts"}},"my-components-ui-mylabel--basic":{"id":"my-components-ui-mylabel--basic","name":"Basic","title":"My_Components/UI/MyLabel","importPath":"./src/stories/MyLabel.stories.ts","tags":["autodocs","story"],"kind":"My_Components/UI/MyLabel","story":"Basic","parameters":{"__id":"my-components-ui-mylabel--basic","docsOnly":false,"fileName":"./src/stories/MyLabel.stories.ts"}},"my-components-ui-mylabel--all-caps":{"id":"my-components-ui-mylabel--all-caps","name":"All Caps","title":"My_Components/UI/MyLabel","importPath":"./src/stories/MyLabel.stories.ts","tags":["autodocs","story"],"kind":"My_Components/UI/MyLabel","story":"All Caps","parameters":{"__id":"my-components-ui-mylabel--all-caps","docsOnly":false,"fileName":"./src/stories/MyLabel.stories.ts"}},"my-components-ui-mylabel--secondary":{"id":"my-components-ui-mylabel--secondary","name":"Secondary","title":"My_Components/UI/MyLabel","importPath":"./src/stories/MyLabel.stories.ts","tags":["autodocs","story"],"kind":"My_Components/UI/MyLabel","story":"Secondary","parameters":{"__id":"my-components-ui-mylabel--secondary","docsOnly":false,"fileName":"./src/stories/MyLabel.stories.ts"}},"my-components-ui-mylabel--custom-color":{"id":"my-components-ui-mylabel--custom-color","name":"Custom Color","title":"My_Components/UI/MyLabel","importPath":"./src/stories/MyLabel.stories.ts","tags":["autodocs","story"],"kind":"My_Components/UI/MyLabel","story":"Custom Color","parameters":{"__id":"my-components-ui-mylabel--custom-color","docsOnly":false,"fileName":"./src/stories/MyLabel.stories.ts"}},"my-components-ui-mylabel--custom-background-color":{"id":"my-components-ui-mylabel--custom-background-color","name":"Custom Background Color","title":"My_Components/UI/MyLabel","importPath":"./src/stories/MyLabel.stories.ts","tags":["autodocs","story"],"kind":"My_Components/UI/MyLabel","story":"Custom Background Color","parameters":{"__id":"my-components-ui-mylabel--custom-background-color","docsOnly":false,"fileName":"./src/stories/MyLabel.stories.ts"}},"example-page--logged-out":{"id":"example-page--logged-out","name":"Logged Out","title":"Example/Page","importPath":"./src/stories/Page.stories.ts","tags":["story"],"kind":"Example/Page","story":"Logged Out","parameters":{"__id":"example-page--logged-out","docsOnly":false,"fileName":"./src/stories/Page.stories.ts"}},"example-page--logged-in":{"id":"example-page--logged-in","name":"Logged In","title":"Example/Page","importPath":"./src/stories/Page.stories.ts","tags":["play-fn","story"],"kind":"Example/Page","story":"Logged In","parameters":{"__id":"example-page--logged-in","docsOnly":false,"fileName":"./src/stories/Page.stories.ts"}},"guide-storybook-task--docs":{"id":"guide-storybook-task--docs","title":"Guide_Storybook/Task","name":"Docs","importPath":"./src/stories/Task.stories.ts","tags":["autodocs","docs"],"storiesImports":[],"kind":"Guide_Storybook/Task","story":"Docs","parameters":{"__id":"guide-storybook-task--docs","docsOnly":true,"fileName":"./src/stories/Task.stories.ts"}},"guide-storybook-task--default":{"id":"guide-storybook-task--default","name":"Default","title":"Guide_Storybook/Task","importPath":"./src/stories/Task.stories.ts","tags":["autodocs","story"],"kind":"Guide_Storybook/Task","story":"Default","parameters":{"__id":"guide-storybook-task--default","docsOnly":false,"fileName":"./src/stories/Task.stories.ts"}},"guide-storybook-task--pinned":{"id":"guide-storybook-task--pinned","name":"Pinned","title":"Guide_Storybook/Task","importPath":"./src/stories/Task.stories.ts","tags":["autodocs","story"],"kind":"Guide_Storybook/Task","story":"Pinned","parameters":{"__id":"guide-storybook-task--pinned","docsOnly":false,"fileName":"./src/stories/Task.stories.ts"}},"guide-storybook-task--archived":{"id":"guide-storybook-task--archived","name":"Archived","title":"Guide_Storybook/Task","importPath":"./src/stories/Task.stories.ts","tags":["autodocs","story"],"kind":"Guide_Storybook/Task","story":"Archived","parameters":{"__id":"guide-storybook-task--archived","docsOnly":false,"fileName":"./src/stories/Task.stories.ts"}},"guide-storybook-tasklist--docs":{"id":"guide-storybook-tasklist--docs","title":"Guide_Storybook/TaskList","name":"Docs","importPath":"./src/stories/TaskList.stories.tsx","tags":["autodocs","docs"],"storiesImports":[],"kind":"Guide_Storybook/TaskList","story":"Docs","parameters":{"__id":"guide-storybook-tasklist--docs","docsOnly":true,"fileName":"./src/stories/TaskList.stories.tsx"}},"guide-storybook-tasklist--default":{"id":"guide-storybook-tasklist--default","name":"Default","title":"Guide_Storybook/TaskList","importPath":"./src/stories/TaskList.stories.tsx","tags":["autodocs","story"],"kind":"Guide_Storybook/TaskList","story":"Default","parameters":{"__id":"guide-storybook-tasklist--default","docsOnly":false,"fileName":"./src/stories/TaskList.stories.tsx"}},"guide-storybook-tasklist--with-pinned-tasks":{"id":"guide-storybook-tasklist--with-pinned-tasks","name":"With Pinned Tasks","title":"Guide_Storybook/TaskList","importPath":"./src/stories/TaskList.stories.tsx","tags":["autodocs","story"],"kind":"Guide_Storybook/TaskList","story":"With Pinned Tasks","parameters":{"__id":"guide-storybook-tasklist--with-pinned-tasks","docsOnly":false,"fileName":"./src/stories/TaskList.stories.tsx"}},"guide-storybook-tasklist--loading":{"id":"guide-storybook-tasklist--loading","name":"Loading","title":"Guide_Storybook/TaskList","importPath":"./src/stories/TaskList.stories.tsx","tags":["autodocs","story"],"kind":"Guide_Storybook/TaskList","story":"Loading","parameters":{"__id":"guide-storybook-tasklist--loading","docsOnly":false,"fileName":"./src/stories/TaskList.stories.tsx"}},"guide-storybook-tasklist--empty":{"id":"guide-storybook-tasklist--empty","name":"Empty","title":"Guide_Storybook/TaskList","importPath":"./src/stories/TaskList.stories.tsx","tags":["autodocs","story"],"kind":"Guide_Storybook/TaskList","story":"Empty","parameters":{"__id":"guide-storybook-tasklist--empty","docsOnly":false,"fileName":"./src/stories/TaskList.stories.tsx"}}}}
